zenkly/__init__.py
zenkly/schemas/macro.schema
zenkly/scripts/__init__.py
zenkly/scripts/constants.py
zenkly/scripts/utilities.py
zenkly/scripts/zenkly.py
zenkly/scripts/commands/__init__.py
zenkly/scripts/commands/add_macros.py
zenkly/scripts/commands/backup_guide.py
zenkly/scripts/commands/configure.py
zenkly/scripts/commands/create_article_mapping.py
zenkly/scripts/commands/get_automations.py
zenkly/scripts/commands/get_macros.py
zenkly/scripts/commands/get_triggers.py
zenkly/scripts/commands/get_views.py
zenkly/scripts/commands/show_brands.py
zenkly/scripts/commands/update_macros.py
zenkly/scripts/commands/upload_theme.py
zenkly-0.1.24.dist-info/LICENSE.txt
zenkly-0.1.24.dist-info/METADATA
zenkly-0.1.24.dist-info/WHEEL
zenkly-0.1.24.dist-info/entry_points.txt
zenkly-0.1.24.dist-info/top_level.txt
zenkly-0.1.24.dist-info/RECORD
