Metadata-Version: 2.1
Name: zenkly
Version: 0.1.24
Summary: CLI for Zendesk admin tasks
Home-page: https://github.com/zenahirsch/zenkly
Author: Zena Hirsch
Author-email: hirsch.zena@gmail.com
License: UNKNOWN
Platform: UNKNOWN
Requires-Python: >=3.6
Requires-Dist: Click
Requires-Dist: simplejson
Requires-Dist: requests
Requires-Dist: jsonschema
Requires-Dist: colorama
Requires-Dist: configparser
Requires-Dist: gitpython
Requires-Dist: tabulate
